{
  "version": "v195",
  "updated": "2026-07-17T12:28:50.429Z",
  "summary": {
    "fixtures": 56,
    "qualified": 1,
    "rejected": 55,
    "highConflict": 0
  },
  "fixtures": [
    {
      "id": 1492296,
      "date": "2026-07-23",
      "home": "Internacional",
      "away": "Cruzeiro",
      "league": "Serie A",
      "version": "v195",
      "bet": false,
      "market": "No Bet",
      "candidate": "Under 3.5 Goals",
      "score": 76.3,
      "support": 0.66,
      "supporters": [
        "League Bias"
      ],
      "independence": 1,
      "exactSupport": 1,
      "conflictIndex": 0,
      "alternatives": [
        {
          "market": "First Half Over 0.5",
          "support": 0.45,
          "engines": [
            "Halves"
          ]
        }
      ],
      "reason": "Consensus rejected: support, independence or conflict threshold failed."
    },
    {
      "id": 1492298,
      "date": "2026-07-23",
      "home": "Sao Paulo",
      "away": "Atletico Paranaense",
      "league": "Serie A",
      "version": "v195",
      "bet": false,
      "market": "No Bet",
      "candidate": "Under 3.5 Goals",
      "score": 76.1,
      "support": 0.63,
      "supporters": [
        "League Bias"
      ],
      "independence": 1,
      "exactSupport": 1,
      "conflictIndex": 0,
      "alternatives": [],
      "reason": "Consensus rejected: support, independence or conflict threshold failed."
    },
    {
      "id": 1492292,
      "date": "2026-07-23",
      "home": "Chapecoense-sc",
      "away": "Flamengo",
      "league": "Serie A",
      "version": "v195",
      "bet": false,
      "market": "No Bet",
      "candidate": "Double Chance X2",
      "score": 80.3,
      "support": 1.27,
      "supporters": [
        "PurePPG Ultra",
        "PurePPG Apex",
        "Trend"
      ],
      "independence": 2,
      "exactSupport": 3,
      "conflictIndex": 0,
      "alternatives": [
        {
          "market": "Second Half Over 0.5",
          "support": 0.77,
          "engines": [
            "Halves"
          ]
        },
        {
          "market": "Under 3.5 Goals",
          "support": 0.63,
          "engines": [
            "League Bias"
          ]
        },
        {
          "market": "Away DNB",
          "support": 0.55,
          "engines": [
            "PurePPG Elite"
          ]
        }
      ],
      "reason": "Consensus rejected: support, independence or conflict threshold failed."
    },
    {
      "id": 1514240,
      "date": "2026-07-23",
      "home": "Leiknir R.",
      "away": "Throttur Reykjavik",
      "league": "1. Deild",
      "version": "v195",
      "bet": false,
      "market": "No Bet",
      "candidate": "Second Half Over 0.5",
      "score": 76.5,
      "support": 0.74,
      "supporters": [
        "Halves"
      ],
      "independence": 1,
      "exactSupport": 1,
      "conflictIndex": 0,
      "alternatives": [],
      "reason": "Consensus rejected: support, independence or conflict threshold failed."
    },
    {
      "id": 1492141,
      "date": "2026-07-23",
      "home": "Botafogo",
      "away": "Vitoria",
      "league": "Serie A",
      "version": "v195",
      "bet": false,
      "market": "No Bet",
      "candidate": "Home Team Over 0.5 Goals",
      "score": 76.9,
      "support": 0.82,
      "supporters": [
        "Trend"
      ],
      "independence": 1,
      "exactSupport": 1,
      "conflictIndex": 0,
      "alternatives": [
        {
          "market": "Under 3.5 Goals",
          "support": 0.6,
          "engines": [
            "League Bias"
          ]
        },
        {
          "market": "Second Half Over 0.5",
          "support": 0.56,
          "engines": [
            "Halves"
          ]
        },
        {
          "market": "Double Chance 1X",
          "support": 0.45,
          "engines": [
            "PurePPG Ultra"
          ]
        }
      ],
      "reason": "Consensus rejected: support, independence or conflict threshold failed."
    },
    {
      "id": 1492293,
      "date": "2026-07-23",
      "home": "Corinthians",
      "away": "Remo",
      "league": "Serie A",
      "version": "v195",
      "bet": false,
      "market": "No Bet",
      "candidate": "Under 3.5 Goals",
      "score": 76.3,
      "support": 0.66,
      "supporters": [
        "League Bias"
      ],
      "independence": 1,
      "exactSupport": 1,
      "conflictIndex": 0,
      "alternatives": [],
      "reason": "Consensus rejected: support, independence or conflict threshold failed."
    },
    {
      "id": 1507007,
      "date": "2026-07-22",
      "home": "Bucheon FC 1995",
      "away": "FC Anyang",
      "league": "K League 1",
      "version": "v195",
      "bet": false,
      "market": "No Bet",
      "candidate": "Under 3.5 Goals",
      "score": 76.4,
      "support": 0.69,
      "supporters": [
        "League Bias"
      ],
      "independence": 1,
      "exactSupport": 1,
      "conflictIndex": 0,
      "alternatives": [
        {
          "market": "Double Chance X2",
          "support": 0.66,
          "engines": [
            "Trend"
          ]
        }
      ],
      "reason": "Consensus rejected: support, independence or conflict threshold failed."
    },
    {
      "id": 1507008,
      "date": "2026-07-22",
      "home": "Gwangju FC",
      "away": "Gimcheon Sangmu FC",
      "league": "K League 1",
      "version": "v195",
      "bet": false,
      "market": "No Bet",
      "candidate": "Under 3.5 Goals",
      "score": 76.5,
      "support": 0.73,
      "supporters": [
        "League Bias"
      ],
      "independence": 1,
      "exactSupport": 1,
      "conflictIndex": 0,
      "alternatives": [
        {
          "market": "Second Half Over 0.5",
          "support": 0.51,
          "engines": [
            "Halves"
          ]
        }
      ],
      "reason": "Consensus rejected: support, independence or conflict threshold failed."
    },
    {
      "id": 1507009,
      "date": "2026-07-22",
      "home": "FC Seoul",
      "away": "Pohang Steelers",
      "league": "K League 1",
      "version": "v195",
      "bet": false,
      "market": "No Bet",
      "candidate": "Under 3.5 Goals",
      "score": 76.2,
      "support": 0.66,
      "supporters": [
        "League Bias"
      ],
      "independence": 1,
      "exactSupport": 1,
      "conflictIndex": 0,
      "alternatives": [
        {
          "market": "First Half Under 1.5",
          "support": 0.45,
          "engines": [
            "Halves"
          ]
        }
      ],
      "reason": "Consensus rejected: support, independence or conflict threshold failed."
    },
    {
      "id": 1492294,
      "date": "2026-07-22",
      "home": "Coritiba",
      "away": "Palmeiras",
      "league": "Serie A",
      "version": "v195",
      "bet": false,
      "market": "No Bet",
      "candidate": "Under 3.5 Goals",
      "score": 76.3,
      "support": 0.66,
      "supporters": [
        "League Bias"
      ],
      "independence": 1,
      "exactSupport": 1,
      "conflictIndex": 0,
      "alternatives": [
        {
          "market": "First Half Over 0.5",
          "support": 0.49,
          "engines": [
            "Halves"
          ]
        }
      ],
      "reason": "Consensus rejected: support, independence or conflict threshold failed."
    },
    {
      "id": 1507004,
      "date": "2026-07-21",
      "home": "Jeju United FC",
      "away": "Gangwon FC",
      "league": "K League 1",
      "version": "v195",
      "bet": true,
      "market": "Under 3.5 Goals",
      "candidate": "Under 3.5 Goals",
      "score": 84.8,
      "support": 2,
      "supporters": [
        "Trend",
        "Streaks",
        "League Bias"
      ],
      "independence": 3,
      "exactSupport": 3,
      "conflictIndex": 0,
      "alternatives": [
        {
          "market": "Double Chance X2",
          "support": 0.59,
          "engines": [
            "PurePPG Ultra"
          ]
        },
        {
          "market": "Away DNB",
          "support": 0.45,
          "engines": [
            "PurePPG Normal"
          ]
        }
      ],
      "reason": "3 engines across 3 independent evidence groups support the exact market."
    },
    {
      "id": 1507005,
      "date": "2026-07-21",
      "home": "Jeonbuk Motors",
      "away": "Daejeon Citizen",
      "league": "K League 1",
      "version": "v195",
      "bet": false,
      "market": "No Bet",
      "candidate": "Under 3.5 Goals",
      "score": 76.1,
      "support": 0.63,
      "supporters": [
        "League Bias"
      ],
      "independence": 1,
      "exactSupport": 1,
      "conflictIndex": 0,
      "alternatives": [
        {
          "market": "Double Chance 1X",
          "support": 0.59,
          "engines": [
            "PurePPG Normal",
            "PurePPG Strict",
            "PurePPG Ultra"
          ]
        },
        {
          "market": "First Half Under 1.5",
          "support": 0.4,
          "engines": [
            "Halves"
          ]
        }
      ],
      "reason": "Consensus rejected: support, independence or conflict threshold failed."
    },
    {
      "id": 1507006,
      "date": "2026-07-21",
      "home": "Ulsan Hyundai FC",
      "away": "Incheon United",
      "league": "K League 1",
      "version": "v195",
      "bet": false,
      "market": "No Bet",
      "candidate": "Under 3.5 Goals",
      "score": 76.3,
      "support": 0.66,
      "supporters": [
        "League Bias"
      ],
      "independence": 1,
      "exactSupport": 1,
      "conflictIndex": 0,
      "alternatives": [],
      "reason": "Consensus rejected: support, independence or conflict threshold failed."
    },
    {
      "id": 1504266,
      "date": "2026-07-21",
      "home": "KäPa",
      "away": "Klubi-04",
      "league": "Ykkösliiga",
      "version": "v195",
      "bet": false,
      "market": "No Bet",
      "candidate": "Under 3.5 Goals",
      "score": 75.2,
      "support": 0.4,
      "supporters": [
        "League Bias"
      ],
      "independence": 1,
      "exactSupport": 1,
      "conflictIndex": 0,
      "alternatives": [],
      "reason": "Consensus rejected: support, independence or conflict threshold failed."
    },
    {
      "id": 1492290,
      "date": "2026-07-21",
      "home": "Atletico-MG",
      "away": "Bahia",
      "league": "Serie A",
      "version": "v195",
      "bet": false,
      "market": "No Bet",
      "candidate": "Under 3.5 Goals",
      "score": 76.3,
      "support": 0.66,
      "supporters": [
        "League Bias"
      ],
      "independence": 1,
      "exactSupport": 1,
      "conflictIndex": 0,
      "alternatives": [
        {
          "market": "First Half Over 0.5",
          "support": 0.53,
          "engines": [
            "Halves"
          ]
        }
      ],
      "reason": "Consensus rejected: support, independence or conflict threshold failed."
    },
    {
      "id": 1514236,
      "date": "2026-07-20",
      "home": "HK Kopavogur",
      "away": "Vestri",
      "league": "1. Deild",
      "version": "v195",
      "bet": false,
      "market": "No Bet",
      "candidate": "Second Half Over 0.5",
      "score": 76.8,
      "support": 0.8,
      "supporters": [
        "Halves"
      ],
      "independence": 1,
      "exactSupport": 1,
      "conflictIndex": 0,
      "alternatives": [],
      "reason": "Consensus rejected: support, independence or conflict threshold failed."
    },
    {
      "id": 1507003,
      "date": "2026-07-19",
      "home": "Bucheon FC 1995",
      "away": "FC Seoul",
      "league": "K League 1",
      "version": "v195",
      "bet": false,
      "market": "No Bet",
      "candidate": "Double Chance X2",
      "score": 81.2,
      "support": 1.51,
      "supporters": [
        "PurePPG Ultra",
        "Trend"
      ],
      "independence": 2,
      "exactSupport": 2,
      "conflictIndex": 0,
      "alternatives": [
        {
          "market": "Away Win",
          "support": 0.85,
          "engines": [
            "PurePPG Normal",
            "PurePPG Strict"
          ]
        },
        {
          "market": "Under 3.5 Goals",
          "support": 0.66,
          "engines": [
            "League Bias"
          ]
        },
        {
          "market": "Away DNB",
          "support": 0.62,
          "engines": [
            "PurePPG Elite",
            "PurePPG Apex"
          ]
        }
      ],
      "reason": "Consensus rejected: support, independence or conflict threshold failed."
    },
    {
      "id": 1507002,
      "date": "2026-07-19",
      "home": "FC Anyang",
      "away": "Gwangju FC",
      "league": "K League 1",
      "version": "v195",
      "bet": false,
      "market": "No Bet",
      "candidate": "Under 3.5 Goals",
      "score": 76.4,
      "support": 0.69,
      "supporters": [
        "League Bias"
      ],
      "independence": 1,
      "exactSupport": 1,
      "conflictIndex": 0,
      "alternatives": [
        {
          "market": "Second Half Over 0.5",
          "support": 0.64,
          "engines": [
            "Halves"
          ]
        }
      ],
      "reason": "Consensus rejected: support, independence or conflict threshold failed."
    },
    {
      "id": 1520546,
      "date": "2026-07-18",
      "home": "Dangjin Citizen",
      "away": "Jeonbuk Motors II",
      "league": "K3 League",
      "version": "v195",
      "bet": false,
      "market": "No Bet",
      "candidate": "Second Half Over 0.5",
      "score": 76.2,
      "support": 0.64,
      "supporters": [
        "Halves"
      ],
      "independence": 1,
      "exactSupport": 1,
      "conflictIndex": 0,
      "alternatives": [
        {
          "market": "Home Team Over 0.5 Goals",
          "support": 0.56,
          "engines": [
            "Trend"
          ]
        }
      ],
      "reason": "Consensus rejected: support, independence or conflict threshold failed."
    },
    {
      "id": 1506999,
      "date": "2026-07-18",
      "home": "Gangwon FC",
      "away": "Gimcheon Sangmu FC",
      "league": "K League 1",
      "version": "v195",
      "bet": false,
      "market": "No Bet",
      "candidate": "Double Chance 1X",
      "score": 76.9,
      "support": 0.82,
      "supporters": [
        "PurePPG Ultra"
      ],
      "independence": 1,
      "exactSupport": 1,
      "conflictIndex": 0,
      "alternatives": [
        {
          "market": "Under 3.5 Goals",
          "support": 0.73,
          "engines": [
            "League Bias"
          ]
        },
        {
          "market": "Home DNB",
          "support": 0.46,
          "engines": [
            "PurePPG Normal"
          ]
        }
      ],
      "reason": "Consensus rejected: support, independence or conflict threshold failed."
    },
    {
      "id": 1506998,
      "date": "2026-07-18",
      "home": "Daejeon Citizen",
      "away": "Ulsan Hyundai FC",
      "league": "K League 1",
      "version": "v195",
      "bet": false,
      "market": "No Bet",
      "candidate": "Under 3.5 Goals",
      "score": 76.1,
      "support": 0.63,
      "supporters": [
        "League Bias"
      ],
      "independence": 1,
      "exactSupport": 1,
      "conflictIndex": 0,
      "alternatives": [],
      "reason": "Consensus rejected: support, independence or conflict threshold failed."
    },
    {
      "id": 1507001,
      "date": "2026-07-18",
      "home": "Jeju United FC",
      "away": "Pohang Steelers",
      "league": "K League 1",
      "version": "v195",
      "bet": false,
      "market": "No Bet",
      "candidate": "Under 3.5 Goals",
      "score": 76.5,
      "support": 0.73,
      "supporters": [
        "League Bias"
      ],
      "independence": 1,
      "exactSupport": 1,
      "conflictIndex": 0,
      "alternatives": [
        {
          "market": "Away DNB",
          "support": 0.69,
          "engines": [
            "PurePPG Strict",
            "PurePPG Ultra"
          ]
        },
        {
          "market": "First Half Under 1.5",
          "support": 0.5,
          "engines": [
            "Halves"
          ]
        },
        {
          "market": "Double Chance X2",
          "support": 0.4,
          "engines": [
            "Trend"
          ]
        }
      ],
      "reason": "Consensus rejected: support, independence or conflict threshold failed."
    },
    {
      "id": 1507000,
      "date": "2026-07-18",
      "home": "Incheon United",
      "away": "Jeonbuk Motors",
      "league": "K League 1",
      "version": "v195",
      "bet": false,
      "market": "No Bet",
      "candidate": "Under 3.5 Goals",
      "score": 76.3,
      "support": 0.66,
      "supporters": [
        "League Bias"
      ],
      "independence": 1,
      "exactSupport": 1,
      "conflictIndex": 0,
      "alternatives": [
        {
          "market": "Double Chance X2",
          "support": 0.35,
          "engines": [
            "Trend"
          ]
        }
      ],
      "reason": "Consensus rejected: support, independence or conflict threshold failed."
    },
    {
      "id": 1528656,
      "date": "2026-07-18",
      "home": "Meizhou Kejia",
      "away": "Dalian Huayi",
      "league": "League One",
      "version": "v195",
      "bet": false,
      "market": "No Bet",
      "candidate": "First Half Over 0.5",
      "score": 75.2,
      "support": 0.39,
      "supporters": [
        "Halves"
      ],
      "independence": 1,
      "exactSupport": 1,
      "conflictIndex": 0,
      "alternatives": [],
      "reason": "Consensus rejected: support, independence or conflict threshold failed."
    },
    {
      "id": 1528657,
      "date": "2026-07-18",
      "home": "Nanjing City",
      "away": "Guangzhou E-Power",
      "league": "League One",
      "version": "v195",
      "bet": false,
      "market": "No Bet",
      "candidate": "Home Team Over 0.5 Goals",
      "score": 75.6,
      "support": 0.49,
      "supporters": [
        "League Bias"
      ],
      "independence": 1,
      "exactSupport": 1,
      "conflictIndex": 0,
      "alternatives": [],
      "reason": "Consensus rejected: support, independence or conflict threshold failed."
    },
    {
      "id": 1528655,
      "date": "2026-07-18",
      "home": "Guangxi Hengchen",
      "away": "Shaanxi Union",
      "league": "League One",
      "version": "v195",
      "bet": false,
      "market": "No Bet",
      "candidate": "Second Half Over 0.5",
      "score": 76,
      "support": 0.59,
      "supporters": [
        "Halves"
      ],
      "independence": 1,
      "exactSupport": 1,
      "conflictIndex": 0,
      "alternatives": [
        {
          "market": "Double Chance 1X",
          "support": 0.53,
          "engines": [
            "Trend"
          ]
        }
      ],
      "reason": "Consensus rejected: support, independence or conflict threshold failed."
    },
    {
      "id": 1528777,
      "date": "2026-07-18",
      "home": "Heilongjiang Lava Spring",
      "away": "Ningbo Professional",
      "league": "League One",
      "version": "v195",
      "bet": false,
      "market": "No Bet",
      "candidate": "First Half Over 0.5",
      "score": 75.4,
      "support": 0.45,
      "supporters": [
        "Halves"
      ],
      "independence": 1,
      "exactSupport": 1,
      "conflictIndex": 0,
      "alternatives": [],
      "reason": "Consensus rejected: support, independence or conflict threshold failed."
    },
    {
      "id": 1504264,
      "date": "2026-07-18",
      "home": "EIF",
      "away": "JäPS",
      "league": "Ykkösliiga",
      "version": "v195",
      "bet": false,
      "market": "No Bet",
      "candidate": "Second Half Over 0.5",
      "score": 76.5,
      "support": 0.74,
      "supporters": [
        "Halves"
      ],
      "independence": 1,
      "exactSupport": 1,
      "conflictIndex": 0,
      "alternatives": [
        {
          "market": "Under 3.5 Goals",
          "support": 0.36,
          "engines": [
            "League Bias"
          ]
        }
      ],
      "reason": "Consensus rejected: support, independence or conflict threshold failed."
    },
    {
      "id": 1504265,
      "date": "2026-07-18",
      "home": "Kooteepee",
      "away": "PK-35",
      "league": "Ykkösliiga",
      "version": "v195",
      "bet": false,
      "market": "No Bet",
      "candidate": "Second Half Over 0.5",
      "score": 76.5,
      "support": 0.74,
      "supporters": [
        "Halves"
      ],
      "independence": 1,
      "exactSupport": 1,
      "conflictIndex": 0,
      "alternatives": [],
      "reason": "Consensus rejected: support, independence or conflict threshold failed."
    },
    {
      "id": 1514232,
      "date": "2026-07-18",
      "home": "Grindavik",
      "away": "IR Reykjavik",
      "league": "1. Deild",
      "version": "v195",
      "bet": false,
      "market": "No Bet",
      "score": 0,
      "reason": "No engine produced a qualified candidate.",
      "supporters": [],
      "conflictIndex": 0,
      "independence": 0
    },
    {
      "id": 1514233,
      "date": "2026-07-18",
      "home": "Grotta",
      "away": "Ægir",
      "league": "1. Deild",
      "version": "v195",
      "bet": false,
      "market": "No Bet",
      "candidate": "Second Half Over 0.5",
      "score": 76.8,
      "support": 0.8,
      "supporters": [
        "Halves"
      ],
      "independence": 1,
      "exactSupport": 1,
      "conflictIndex": 0,
      "alternatives": [],
      "reason": "Consensus rejected: support, independence or conflict threshold failed."
    },
    {
      "id": 1514235,
      "date": "2026-07-18",
      "home": "Throttur Reykjavik",
      "away": "Völsungur",
      "league": "1. Deild",
      "version": "v195",
      "bet": false,
      "market": "No Bet",
      "candidate": "Second Half Over 0.5",
      "score": 76.8,
      "support": 0.8,
      "supporters": [
        "Halves"
      ],
      "independence": 1,
      "exactSupport": 1,
      "conflictIndex": 0,
      "alternatives": [
        {
          "market": "Home Team Over 0.5 Goals",
          "support": 0.47,
          "engines": [
            "League Bias"
          ]
        }
      ],
      "reason": "Consensus rejected: support, independence or conflict threshold failed."
    },
    {
      "id": 1519094,
      "date": "2026-07-17",
      "home": "Rostov U19",
      "away": "Chertanovo U20",
      "league": "Youth Championship",
      "version": "v195",
      "bet": false,
      "market": "No Bet",
      "candidate": "Second Half Over 0.5",
      "score": 76.9,
      "support": 0.83,
      "supporters": [
        "Halves"
      ],
      "independence": 1,
      "exactSupport": 1,
      "conflictIndex": 0,
      "alternatives": [],
      "reason": "Consensus rejected: support, independence or conflict threshold failed."
    },
    {
      "id": 1519093,
      "date": "2026-07-17",
      "home": "Fakel U19",
      "away": "Zenit U19",
      "league": "Youth Championship",
      "version": "v195",
      "bet": false,
      "market": "No Bet",
      "candidate": "Second Half Over 0.5",
      "score": 76.9,
      "support": 0.83,
      "supporters": [
        "Halves"
      ],
      "independence": 1,
      "exactSupport": 1,
      "conflictIndex": 0,
      "alternatives": [
        {
          "market": "Home Team Over 0.5 Goals",
          "support": 0.45,
          "engines": [
            "League Bias"
          ]
        }
      ],
      "reason": "Consensus rejected: support, independence or conflict threshold failed."
    },
    {
      "id": 1504263,
      "date": "2026-07-17",
      "home": "Klubi-04",
      "away": "Haka",
      "league": "Ykkösliiga",
      "version": "v195",
      "bet": false,
      "market": "No Bet",
      "candidate": "First Half Under 1.5",
      "score": 75.7,
      "support": 0.52,
      "supporters": [
        "Halves"
      ],
      "independence": 1,
      "exactSupport": 1,
      "conflictIndex": 0,
      "alternatives": [],
      "reason": "Consensus rejected: support, independence or conflict threshold failed."
    },
    {
      "id": 1504262,
      "date": "2026-07-17",
      "home": "KäPa",
      "away": "SJK Akatemia",
      "league": "Ykkösliiga",
      "version": "v195",
      "bet": false,
      "market": "No Bet",
      "candidate": "Under 3.5 Goals",
      "score": 75.2,
      "support": 0.4,
      "supporters": [
        "League Bias"
      ],
      "independence": 1,
      "exactSupport": 1,
      "conflictIndex": 0,
      "alternatives": [],
      "reason": "Consensus rejected: support, independence or conflict threshold failed."
    },
    {
      "id": 1519096,
      "date": "2026-07-17",
      "home": "Krasnodar U19",
      "away": "CSKA Moskva U19",
      "league": "Youth Championship",
      "version": "v195",
      "bet": false,
      "market": "No Bet",
      "candidate": "Over 1.5 Goals",
      "score": 80.3,
      "support": 1.28,
      "supporters": [
        "Trend",
        "League Bias"
      ],
      "independence": 2,
      "exactSupport": 2,
      "conflictIndex": 0,
      "alternatives": [
        {
          "market": "Second Half Over 0.5",
          "support": 0.83,
          "engines": [
            "Halves"
          ]
        }
      ],
      "reason": "Consensus rejected: support, independence or conflict threshold failed."
    },
    {
      "id": 1514234,
      "date": "2026-07-17",
      "home": "Fylkir",
      "away": "Njardvik",
      "league": "1. Deild",
      "version": "v195",
      "bet": false,
      "market": "No Bet",
      "candidate": "Second Half Over 0.5",
      "score": 76.2,
      "support": 0.66,
      "supporters": [
        "Halves"
      ],
      "independence": 1,
      "exactSupport": 1,
      "conflictIndex": 0,
      "alternatives": [],
      "reason": "Consensus rejected: support, independence or conflict threshold failed."
    },
    {
      "id": 1492140,
      "date": "2026-07-17",
      "home": "Bahia",
      "away": "Chapecoense-sc",
      "league": "Serie A",
      "version": "v195",
      "bet": false,
      "market": "No Bet",
      "candidate": "Home Team Over 0.5 Goals",
      "score": 77,
      "support": 0.85,
      "supporters": [
        "Trend"
      ],
      "independence": 1,
      "exactSupport": 1,
      "conflictIndex": 0,
      "alternatives": [
        {
          "market": "Under 3.5 Goals",
          "support": 0.66,
          "engines": [
            "League Bias"
          ]
        },
        {
          "market": "Second Half Over 0.5",
          "support": 0.53,
          "engines": [
            "Halves"
          ]
        }
      ],
      "reason": "Consensus rejected: support, independence or conflict threshold failed."
    },
    {
      "id": 1492295,
      "date": "2026-07-17",
      "home": "Fluminense",
      "away": "RB Bragantino",
      "league": "Serie A",
      "version": "v195",
      "bet": false,
      "market": "No Bet",
      "candidate": "Under 3.5 Goals",
      "score": 76.3,
      "support": 0.66,
      "supporters": [
        "League Bias"
      ],
      "independence": 1,
      "exactSupport": 1,
      "conflictIndex": 0,
      "alternatives": [
        {
          "market": "First Half Over 0.5",
          "support": 0.45,
          "engines": [
            "Halves"
          ]
        }
      ],
      "reason": "Consensus rejected: support, independence or conflict threshold failed."
    },
    {
      "id": 1492297,
      "date": "2026-07-17",
      "home": "Mirassol",
      "away": "Gremio",
      "league": "Serie A",
      "version": "v195",
      "bet": false,
      "market": "No Bet",
      "candidate": "Under 3.5 Goals",
      "score": 76.3,
      "support": 0.66,
      "supporters": [
        "League Bias"
      ],
      "independence": 1,
      "exactSupport": 1,
      "conflictIndex": 0,
      "alternatives": [
        {
          "market": "Second Half Over 0.5",
          "support": 0.47,
          "engines": [
            "Halves"
          ]
        }
      ],
      "reason": "Consensus rejected: support, independence or conflict threshold failed."
    },
    {
      "id": 1523779,
      "date": "2026-07-15",
      "home": "Kahibah",
      "away": "Maitland",
      "league": "Northern NSW NPL",
      "version": "v195",
      "bet": false,
      "market": "No Bet",
      "candidate": "Away Win",
      "score": 77,
      "support": 0.85,
      "supporters": [
        "PurePPG Normal",
        "PurePPG Strict"
      ],
      "independence": 1,
      "exactSupport": 2,
      "conflictIndex": 0,
      "alternatives": [],
      "reason": "Consensus rejected: support, independence or conflict threshold failed."
    },
    {
      "id": 1554956,
      "date": "2026-07-15",
      "home": "GKS Katowice",
      "away": "Maccabi Netanya",
      "league": "Friendlies Clubs",
      "version": "v195",
      "bet": false,
      "market": "No Bet",
      "score": 0,
      "reason": "No engine produced a qualified candidate.",
      "supporters": [],
      "conflictIndex": 0,
      "independence": 0
    },
    {
      "id": 1554960,
      "date": "2026-07-15",
      "home": "Puszcza Niepołomice",
      "away": "Podhale Nowy Targ",
      "league": "Friendlies Clubs",
      "version": "v195",
      "bet": false,
      "market": "No Bet",
      "score": 0,
      "reason": "No engine produced a qualified candidate.",
      "supporters": [],
      "conflictIndex": 0,
      "independence": 0
    },
    {
      "id": 1554961,
      "date": "2026-07-15",
      "home": "Rilski Sportist",
      "away": "Marek",
      "league": "Friendlies Clubs",
      "version": "v195",
      "bet": false,
      "market": "No Bet",
      "score": 0,
      "reason": "No engine produced a qualified candidate.",
      "supporters": [],
      "conflictIndex": 0,
      "independence": 0
    },
    {
      "id": 1560612,
      "date": "2026-07-15",
      "home": "Dynamo",
      "away": "Krylia Sovetov",
      "league": "Friendlies Clubs",
      "version": "v195",
      "bet": false,
      "market": "No Bet",
      "score": 0,
      "reason": "No engine produced a qualified candidate.",
      "supporters": [],
      "conflictIndex": 0,
      "independence": 0
    },
    {
      "id": 1583315,
      "date": "2026-07-15",
      "home": "Malženice",
      "away": "Zbrojovka Brno",
      "league": "Friendlies Clubs",
      "version": "v195",
      "bet": false,
      "market": "No Bet",
      "score": 0,
      "reason": "No engine produced a qualified candidate.",
      "supporters": [],
      "conflictIndex": 0,
      "independence": 0
    },
    {
      "id": 1554958,
      "date": "2026-07-15",
      "home": "FK Jablonec",
      "away": "Metalist 1925 Kharkiv",
      "league": "Friendlies Clubs",
      "version": "v195",
      "bet": false,
      "market": "No Bet",
      "score": 0,
      "reason": "No engine produced a qualified candidate.",
      "supporters": [],
      "conflictIndex": 0,
      "independence": 0
    },
    {
      "id": 1589267,
      "date": "2026-07-15",
      "home": "Iváncsa",
      "away": "Budafoki LC",
      "league": "Friendlies Clubs",
      "version": "v195",
      "bet": false,
      "market": "No Bet",
      "score": 0,
      "reason": "No engine produced a qualified candidate.",
      "supporters": [],
      "conflictIndex": 0,
      "independence": 0
    },
    {
      "id": 1554800,
      "date": "2026-07-15",
      "home": "Germania Ober-Roden",
      "away": "Kickers Offenbach",
      "league": "Friendlies Clubs",
      "version": "v195",
      "bet": false,
      "market": "No Bet",
      "score": 0,
      "reason": "No engine produced a qualified candidate.",
      "supporters": [],
      "conflictIndex": 0,
      "independence": 0
    },
    {
      "id": 1583314,
      "date": "2026-07-15",
      "home": "Galanta",
      "away": "Piešťany",
      "league": "Friendlies Clubs",
      "version": "v195",
      "bet": false,
      "market": "No Bet",
      "score": 0,
      "reason": "No engine produced a qualified candidate.",
      "supporters": [],
      "conflictIndex": 0,
      "independence": 0
    },
    {
      "id": 1583663,
      "date": "2026-07-15",
      "home": "England U20 W",
      "away": "Colombia U20 W",
      "league": "Friendlies Women",
      "version": "v195",
      "bet": false,
      "market": "No Bet",
      "score": 0,
      "reason": "No engine produced a qualified candidate.",
      "supporters": [],
      "conflictIndex": 0,
      "independence": 0
    },
    {
      "id": 1583325,
      "date": "2026-07-15",
      "home": "Brønshøj",
      "away": "Frem",
      "league": "Friendlies Clubs",
      "version": "v195",
      "bet": false,
      "market": "No Bet",
      "score": 0,
      "reason": "No engine produced a qualified candidate.",
      "supporters": [],
      "conflictIndex": 0,
      "independence": 0
    },
    {
      "id": 1584785,
      "date": "2026-07-15",
      "home": "Neuchatel Xamax FC",
      "away": "Coffrane",
      "league": "Friendlies Clubs",
      "version": "v195",
      "bet": false,
      "market": "No Bet",
      "score": 0,
      "reason": "No engine produced a qualified candidate.",
      "supporters": [],
      "conflictIndex": 0,
      "independence": 0
    },
    {
      "id": 1548852,
      "date": "2026-07-15",
      "home": "Preston",
      "away": "Chorley",
      "league": "Friendlies Clubs",
      "version": "v195",
      "bet": false,
      "market": "No Bet",
      "score": 0,
      "reason": "No engine produced a qualified candidate.",
      "supporters": [],
      "conflictIndex": 0,
      "independence": 0
    },
    {
      "id": 1567636,
      "date": "2026-07-15",
      "home": "Austin",
      "away": "Charlotte",
      "league": "Friendlies Clubs",
      "version": "v195",
      "bet": false,
      "market": "No Bet",
      "score": 0,
      "reason": "No engine produced a qualified candidate.",
      "supporters": [],
      "conflictIndex": 0,
      "independence": 0
    }
  ]
}
